easy_http_requests/__init__.py
easy_http_requests/easy_http_request.py
easy_http_requests/easy_http_response.py
easy_http_requests/exceptions/easy_http_error.py
py.typed
stubs/__init__.py
stubs/easy_http_requests/easy_http_request.pyi
easy_http_requests-0.5.2.dist-info/LICENSE
easy_http_requests-0.5.2.dist-info/METADATA
easy_http_requests-0.5.2.dist-info/WHEEL
easy_http_requests-0.5.2.dist-info/RECORD
